related/__init__.py
related/_init_fields.py
related/converters.py
related/decorators.py
related/dispatchers.py
related/fields.py
related/functions.py
related/types.py
related/validators.py
related-0.7.3.dist-info/LICENSE
related-0.7.3.dist-info/METADATA
related-0.7.3.dist-info/WHEEL
related-0.7.3.dist-info/top_level.txt
related-0.7.3.dist-info/RECORD
