Metadata-Version: 2.1
Name: related
Version: 0.7.3
Summary: Related: Straightforward nested object models in Python
Home-page: https://github.com/genomoncology/related
License: MIT license
Keywords: related object models yaml json dict nested
Classifier: Development Status :: 2 - Pre-Alpha
Classifier: Intended Audience :: Developers
Classifier: License :: OSI Approved :: MIT License
Classifier: Natural Language :: English
Classifier: Programming Language :: Python :: 2
Classifier: Programming Language :: Python :: 2.7
Classifier: Programming Language :: Python :: 3
Classifier: Programming Language :: Python :: 3.4
Classifier: Programming Language :: Python :: 3.5
Classifier: Programming Language :: Python :: 3.6
Classifier: Programming Language :: Python :: 3.7
License-File: LICENSE
Requires-Dist: attrs (>=19.3.0)
Requires-Dist: PyYAML
Requires-Dist: future
Requires-Dist: python-dateutil
Requires-Dist: singledispatch ; python_version < "3.4"
